pyLemma/FDEM1D.cpython-38-darwin.so
pyLemma/FDEM1D.cpython-39-darwin.so
pyLemma/LemmaCore.cpython-38-darwin.so
pyLemma/LemmaCore.cpython-39-darwin.so
pyLemma/Merlin.cpython-38-darwin.so
pyLemma/Merlin.cpython-39-darwin.so
pyLemma/__init__.py
pyLemma-0.4.1.dist-info/METADATA
pyLemma-0.4.1.dist-info/WHEEL
pyLemma-0.4.1.dist-info/top_level.txt
pyLemma-0.4.1.dist-info/RECORD
