Metadata-Version: 2.1
Name: pyLemma
Version: 0.4.1
Summary: PyLemma is a wrapper to Lemma
Home-page: UNKNOWN
Author: Trevor Irons and others
Author-email: Trevor.Irons@lemmasoftware.org
License: UNKNOWN
Platform: UNKNOWN
Classifier: Development Status :: 3 - Alpha
Classifier: Intended Audience :: Developers
Classifier: License :: OSI Approved :: Mozilla Public License 2.0 (MPL 2.0)
Classifier: Topic :: Scientific/Engineering
Classifier: Programming Language :: Python :: 3
